wagtail_cookies_consent/__init__.py
wagtail_cookies_consent/admin.py
wagtail_cookies_consent/apps.py
wagtail_cookies_consent/cache.py
wagtail_cookies_consent/models.py
wagtail_cookies_consent/tests.py
wagtail_cookies_consent/urls.py
wagtail_cookies_consent/util.py
wagtail_cookies_consent/views.py
wagtail_cookies_consent/wagtail_hooks.py
wagtail_cookies_consent/migrations/0001_initial.py
wagtail_cookies_consent/migrations/__init__.py
wagtail_cookies_consent/static/cookies_consent_wagtail/css/bootstrap-custom.css
wagtail_cookies_consent/static/cookies_consent_wagtail/css/cookies_banner.css
wagtail_cookies_consent/static/cookies_consent_wagtail/css/project.css
wagtail_cookies_consent/static/cookies_consent_wagtail/js/bootstrap.bundle.js
wagtail_cookies_consent/static/cookies_consent_wagtail/js/cookies_model_actions.js
wagtail_cookies_consent/static/cookies_consent_wagtail/js/request_options_builder.js
wagtail_cookies_consent/templates/cookies_consent_wagtail/cookies_banner.html
wagtail_cookies_consent/templates/cookies_consent_wagtail/components/cookies_banner.html
wagtail_cookies_consent/templates/cookies_consent_wagtail/components/cookies_model.html
wagtail_cookies_consent/templates/cookies_consent_wagtail/components/model.html
wagtail_cookies_consent/templates/cookies_consent_wagtail/components/model_header.html
wagtail_cookies_consent/templatetags/__init__.py
wagtail_cookies_consent/templatetags/cookie_consent_tags.py
wagtail_cookies_consent-0.1.7.dist-info/METADATA
wagtail_cookies_consent-0.1.7.dist-info/WHEEL
wagtail_cookies_consent-0.1.7.dist-info/top_level.txt
wagtail_cookies_consent-0.1.7.dist-info/RECORD
