Metadata-Version: 2.2
Name: wagtail_cookies_consent
Version: 0.1.7
Summary: 'A Wagtail package for seamless cookies consent integration and management.'
Author-email: Mohammed Alsubaie <mohammed.alsubaie@innosoft.sa>
Classifier: Environment :: Web Environment
Classifier: Framework :: Django
Classifier: Framework :: Django :: 5
Classifier: Intended Audience :: Developers
Classifier: License :: OSI Approved :: BSD License
Classifier: Operating System :: OS Independent
Classifier: Programming Language :: Python
Classifier: Programming Language :: Python :: 3
Classifier: Programming Language :: Python :: 3 :: Only
Classifier: Programming Language :: Python :: 3.10
Classifier: Programming Language :: Python :: 3.11
Classifier: Programming Language :: Python :: 3.12
Classifier: Programming Language :: Python :: 3.13
Classifier: Topic :: Internet :: WWW/HTTP
Classifier: Topic :: Internet :: WWW/HTTP :: Dynamic Content
Requires-Python: >=3.10
Requires-Dist: django>=5
Requires-Dist: wagtail>=6.1.3
Requires-Dist: django-compressor
